l0learn/__init__.py
l0learn/interface.py
l0learn/l0learn.cpython-310-darwin.so
l0learn/models.py
l0learn/version.py
l0learn/include/armadillo
l0learn/include/armadillo_bits/BaseCube_bones.hpp
l0learn/include/armadillo_bits/BaseCube_meat.hpp
l0learn/include/armadillo_bits/Base_bones.hpp
l0learn/include/armadillo_bits/Base_meat.hpp
l0learn/include/armadillo_bits/Col_bones.hpp
l0learn/include/armadillo_bits/Col_meat.hpp
l0learn/include/armadillo_bits/CubeToMatOp_bones.hpp
l0learn/include/armadillo_bits/CubeToMatOp_meat.hpp
l0learn/include/armadillo_bits/Cube_bones.hpp
l0learn/include/armadillo_bits/Cube_meat.hpp
l0learn/include/armadillo_bits/GenCube_bones.hpp
l0learn/include/armadillo_bits/GenCube_meat.hpp
l0learn/include/armadillo_bits/GenSpecialiser.hpp
l0learn/include/armadillo_bits/Gen_bones.hpp
l0learn/include/armadillo_bits/Gen_meat.hpp
l0learn/include/armadillo_bits/GlueCube_bones.hpp
l0learn/include/armadillo_bits/GlueCube_meat.hpp
l0learn/include/armadillo_bits/Glue_bones.hpp
l0learn/include/armadillo_bits/Glue_meat.hpp
l0learn/include/armadillo_bits/MapMat_bones.hpp
l0learn/include/armadillo_bits/MapMat_meat.hpp
l0learn/include/armadillo_bits/Mat_bones.hpp
l0learn/include/armadillo_bits/Mat_meat.hpp
l0learn/include/armadillo_bits/OpCube_bones.hpp
l0learn/include/armadillo_bits/OpCube_meat.hpp
l0learn/include/armadillo_bits/Op_bones.hpp
l0learn/include/armadillo_bits/Op_meat.hpp
l0learn/include/armadillo_bits/Proxy.hpp
l0learn/include/armadillo_bits/ProxyCube.hpp
l0learn/include/armadillo_bits/Row_bones.hpp
l0learn/include/armadillo_bits/Row_meat.hpp
l0learn/include/armadillo_bits/SizeCube_bones.hpp
l0learn/include/armadillo_bits/SizeCube_meat.hpp
l0learn/include/armadillo_bits/SizeMat_bones.hpp
l0learn/include/armadillo_bits/SizeMat_meat.hpp
l0learn/include/armadillo_bits/SpBase_bones.hpp
l0learn/include/armadillo_bits/SpBase_meat.hpp
l0learn/include/armadillo_bits/SpCol_bones.hpp
l0learn/include/armadillo_bits/SpCol_meat.hpp
l0learn-0.4.3.dist-info/LICENSE
l0learn-0.4.3.dist-info/METADATA
l0learn-0.4.3.dist-info/WHEEL
l0learn-0.4.3.dist-info/top_level.txt
l0learn-0.4.3.dist-info/RECORD
