Metadata-Version: 2.1
Name: l0learn
Version: 0.4.3
Summary: L0Learn is a highly efficient framework for solving L0-regularized learning problems.
Home-page: https://github.com/hazimehh/L0Learn
Author: Hussein Hazimeh
Author-email: hazimeh@google.com
Maintainer: Tim Nonet
Maintainer-email: tim.nonet@gmail.com
License: MIT
Project-URL: Source, https://github.com/hazimehh/L0Learn
Project-URL: Tracker, https://github.com/hazimehh/L0Learn/issues
Classifier: Intended Audience :: Science/Research
Classifier: Intended Audience :: Developers
Classifier: Topic :: Scientific/Engineering :: Mathematics
Classifier: Topic :: Software Development :: Libraries :: Python Modules
Classifier: Development Status :: 4 - Beta
Classifier: Programming Language :: C++
Classifier: Programming Language :: Python :: 3.7
Classifier: Programming Language :: Python :: 3.8
Classifier: Programming Language :: Python :: 3.9
Classifier: Programming Language :: Python :: 3.10
Classifier: Operating System :: POSIX
Classifier: Operating System :: MacOS
Classifier: License :: OSI Approved :: MIT License
Requires-Python: >=3.7
License-File: LICENSE
Requires-Dist: numpy >=1.19.0
Requires-Dist: scipy >=1.0.0
Requires-Dist: pandas >=1.0.0
Requires-Dist: matplotlib
Provides-Extra: all
Requires-Dist: hypothesis ; extra == 'all'
Provides-Extra: test
Requires-Dist: hypothesis ; extra == 'test'
